pyright_analysis/__init__.py
pyright_analysis/_utils.py
pyright_analysis/cli.py
pyright_analysis/py.typed
pyright_analysis/schema.py
pyright_analysis/treemap.py
pyright_analysis-1.0.0.dist-info/METADATA
pyright_analysis-1.0.0.dist-info/WHEEL
pyright_analysis-1.0.0.dist-info/entry_points.txt
pyright_analysis-1.0.0.dist-info/licenses/LICENSE.txt
pyright_analysis-1.0.0.dist-info/RECORD
