Metadata-Version: 2.4
Name: pyright-analysis
Version: 1.0.0
Summary: Visualise Python project type completeness
Project-URL: GitHub, https://github.com/mjpieters/pyright-analysis
Project-URL: Issues, https://github.com/mjpieters/pyright-analysis/issues
Project-URL: Changelog, https://github.com/mjpieters/pyright-analysis/blob/master/CHANGELOG.md
Author-email: Martijn Pieters <mj@zopatista.com>
License-Expression: MIT
License-File: LICENSE.txt
Keywords: pyright,type-compleness,visualisation
Classifier: Development Status :: 5 - Production/Stable
Classifier: Environment :: Console
Classifier: Intended Audience :: Developers
Classifier: License :: OSI Approved :: MIT License
Classifier: Topic :: Scientific/Engineering :: Visualization
Classifier: Topic :: Utilities
Classifier: Typing :: Typed
Requires-Python: >=3.12
Requires-Dist: kaleido>=1.0.0rc0
Requires-Dist: plotly>=5.24.1
Requires-Dist: pydantic>=2.10.4
Requires-Dist: typer>=0.15.1
